django_compiler
